langgraph_lib/__init__.py
langgraph_lib/client/__init__.py
langgraph_lib/client/client.py
langgraph_lib/schema/__init__.py
langgraph_lib/schema/schema.py
langgraph_lib/service/__init__.py
langgraph_lib/service/service.py
langgraph_lib-0.1.0.dist-info/LICENSE.txt
langgraph_lib-0.1.0.dist-info/METADATA
langgraph_lib-0.1.0.dist-info/WHEEL
langgraph_lib-0.1.0.dist-info/top_level.txt
langgraph_lib-0.1.0.dist-info/RECORD
